functions_by_madina3006/math_functions.py
functions_by_madina3006-0.3.0.dist-info/WHEEL
functions_by_madina3006-0.3.0.dist-info/METADATA
functions_by_madina3006-0.3.0.dist-info/RECORD
